porthog/__init__.py
porthog/cli.py
porthog/ports.py
porthog/py.typed
porthog/tui.py
porthog-0.1.2.dist-info/METADATA
porthog-0.1.2.dist-info/WHEEL
porthog-0.1.2.dist-info/entry_points.txt
porthog-0.1.2.dist-info/licenses/LICENSE
porthog-0.1.2.dist-info/RECORD
