Metadata-Version: 2.4
Name: porthog
Version: 0.1.2
Summary: CLI/TUI tool to find and kill dev servers hogging your ports
Project-URL: Homepage, https://github.com/pengelbrecht/porthog
Project-URL: Repository, https://github.com/pengelbrecht/porthog
Project-URL: Issues, https://github.com/pengelbrecht/porthog/issues
Author-email: Peter Engelbrecht <peter@engelbrecht.dk>
License: MIT
License-File: LICENSE
Keywords: cli,development,devtools,ports,tui
Classifier: Development Status :: 4 - Beta
Classifier: Environment :: Console
Classifier: Intended Audience :: Developers
Classifier: License :: OSI Approved :: MIT License
Classifier: Operating System :: MacOS
Classifier: Operating System :: POSIX :: Linux
Classifier: Programming Language :: Python :: 3
Classifier: Topic :: Software Development :: Build Tools
Classifier: Topic :: System :: Systems Administration
Requires-Python: >=3.10
Requires-Dist: psutil>=5.9.0
Requires-Dist: rich>=13.0.0
Requires-Dist: textual>=0.40.0
Requires-Dist: typer>=0.9.0
